[
  {
    "type": "blog",
    "url": "https://topupmas.com/digital/331408",
    "title": "Event berhadiah setiap bulan",
    "date": "7 Februari 2025 22:05"
  },
  {
    "type": "blog",
    "url": "https://topupmas.com/digital/329337",
    "title": "Cara ubah harga pada struk pembayaran",
    "date": "27 Januari 2025 10:45"
  },
  {
    "type": "promo",
    "url": "https://topupmas.com/digital/316847",
    "title": "Produk baru beli Paket Telkomsel Super Murah",
    "date": "27 Januari 2025 12:30"
  }
]
